ssh_ipykernel_interrupt/__init__.py
ssh_ipykernel_interrupt/_version.py
ssh_ipykernel_interrupt/labextension/package.json
ssh_ipykernel_interrupt/labextension/static/534.4326ed6c7f37d4e04251.js
ssh_ipykernel_interrupt/labextension/static/568.189ec3b660c587c92522.js
ssh_ipykernel_interrupt/labextension/static/568.de2150183d3fb5d383b8.js
ssh_ipykernel_interrupt/labextension/static/remoteEntry.065d272da6ea2bbb04ba.js
ssh_ipykernel_interrupt/labextension/static/remoteEntry.12dfbd8a20ceafc0a0bc.js
ssh_ipykernel_interrupt/labextension/static/remoteEntry.a6bad887c2f4c5a1cccf.js
ssh_ipykernel_interrupt/labextension/static/style.js
ssh_ipykernel_interrupt-1.1.2.data/data/share/jupyter/labextensions/interrupt_ssh_ipykernel/install.json
ssh_ipykernel_interrupt-1.1.2.data/data/share/jupyter/labextensions/interrupt_ssh_ipykernel/package.json
ssh_ipykernel_interrupt-1.1.2.data/data/share/jupyter/labextensions/interrupt_ssh_ipykernel/static/534.4326ed6c7f37d4e04251.js
ssh_ipykernel_interrupt-1.1.2.data/data/share/jupyter/labextensions/interrupt_ssh_ipykernel/static/568.189ec3b660c587c92522.js
ssh_ipykernel_interrupt-1.1.2.data/data/share/jupyter/labextensions/interrupt_ssh_ipykernel/static/remoteEntry.12dfbd8a20ceafc0a0bc.js
ssh_ipykernel_interrupt-1.1.2.data/data/share/jupyter/labextensions/interrupt_ssh_ipykernel/static/style.js
ssh_ipykernel_interrupt-1.1.2.dist-info/LICENSE
ssh_ipykernel_interrupt-1.1.2.dist-info/METADATA
ssh_ipykernel_interrupt-1.1.2.dist-info/WHEEL
ssh_ipykernel_interrupt-1.1.2.dist-info/top_level.txt
ssh_ipykernel_interrupt-1.1.2.dist-info/RECORD
