Metadata-Version: 2.1
Name: ssh-ipykernel-interrupt
Version: 1.1.2
Summary: Add a button to reliably interrupt a IPython kernel
Home-page: https://github.com/github_username/ssh_ipykernel
Author: Bernhard Walter
Author-email: b_walter@arcor.de
License: BSD-3-Clause
Keywords: Jupyter,JupyterLab,JupyterLab3
Platform: Linux
Platform: Mac OS X
Platform: Windows
Classifier: License :: OSI Approved :: BSD License
Classifier: Programming Language :: Python
Classifier: Programming Language :: Python :: 3
Classifier: Programming Language :: Python :: 3.6
Classifier: Programming Language :: Python :: 3.7
Classifier: Programming Language :: Python :: 3.8
Classifier: Programming Language :: Python :: 3.9
Classifier: Framework :: Jupyter
Requires-Python: >=3.6
Requires-Dist: jupyterlab (~=3.0)
Requires-Dist: jupyter-packaging (<2,~=0.9)
